{    "localbusiness": [
    {
        "name": "Edge of the Cedars",
        "address": "660 W 400 N Blanding UT 84511",
        "phone": "(435) 678-2238",
        "website": "https://stateparks.utah.gov/parks/edge-of-the-cedars",
        "membership": "gold",
        "order": 1,
        "logo": "images/logos/edge.png"
    },
    {
        "name": "The dinasaur museum",
        "address": "754 S 200 W Blanding UT 84511",
        "phone": "(435) 678-3454",
        "website": "http://dinosaur-museum.org",
        "membership": "silver",
        "order": 2,
        "logo": "images/logos/dinasaur.png"
    },
    {
        "name": "Four Corners Inn",
        "address": "131 E Center St Blanding UT 84511",
        "phone": "(435) 678-3257",
        "website": "https://fourcornersinnblanding.com",
        "membership": "bronze",
        "order": 3,
        "logo":"images/logos/four.png"
    },
    {
        "name": "Bears Ears National Monument",
        "address": "365 N Main Monticello UT 84535",
        "phone": "(435) 587-1500",
        "website": "https://www.blm.gov/visit/bears-ears-national-monument",
        "membership": "gold",
        "order": 4,
        "logo": "images/logos/bears.png"
    },
    {
        "name": "Natural Bridges National Monument",
        "address": "HC-60 Box 1 Lake Powell UT 84533",
        "phone": "(435) 692-1234 x616",
        "website": "https://www.nps.gov/nabr/index.htm",
        "membership": "silver",
        "order": 5,
        "logo": "images/logos/natural.png"
    },
    {
        "name": "Goosenecks stake Park",
        "address": "660 W 400 N Blanding UT 84511",
        "phone": "(435) 692-1234 x616",
        "website": "https://stateparks.utah.gov/parks/goosenecks/directions/",
        "membership": "bronze",
        "order": 6,
        "logo": "images/logos/goosenecks.png"
    },
    {
        "name": "Abaja Haven Guest Ranch",
        "address": "5440 N Cedar edge Ln Blanding UT 84511",
        "phone": "(435) 979-3126",
        "website": "http://abajohaven.com",
        "membership": "gold",
        "order": 7,
        "logo": "images/logos/abaja.png"
    },
    {
        "name": "Stone Lizard Lodge",
        "address": "88 W Center St Blanding UT 84511",
        "phone": "(866) 437-9903",
        "website": "https://www.stonelizardlodge.com",
        "membership": "silver",
        "order": 8,
        "logo": "images/logos/stone.png"
    },
    {
        "name": "Blue Mountain RV park",
        "address": "1930 S Main St Blanding UT 84511",
        "phone": "(866) 437-437-9904",
        "website": "https://www.bluemountainrvpark.com",
        "membership": "bronze",
        "order": 9,
        "logo": "images/logos/blue.png"
    },
    {
        "name": "Arch Canyon Inn",
        "address": "755 S Main St Blanding Ut 84511",
        "phone": "(435) 678-3880",
        "website": "http://www.archcanyoninnblanding.com",
        "membership": "gold",
        "order": 10,
        "logo": "images/logos/arch.png"
    },
    {
        "name": "Canyon Country Bowling Center",
        "address": "12 W Center St Blanding UT 84511",
        "phone": "(435) 678-3900",
        "website": "https://www.utahscanyoncountry.com/canyon-country-bowling-center",
        "membership": "silver",
        "order": 11,
        "logo": "images/logos/bowl.png"
    },
    {
        "name": "San Juan Theatre",
        "address": "12 W Center St Blanding UT 84511",
        "phone": "(801) 435-3900",
        "website": "https://www.utahscanyoncountry.com/canyon-country-bowling-center",
        "membership": "bronze",
        "order": 12,
        "logo": "images/logos/theatre.png"
    },
    {
        "name": "Blanding City Visitors center",
        "address": "12 N Grayson Pkwy Blanding UT 84511",
        "phone": "(801) 435-3900",
        "website": "https://www.utahscanyoncountry.com/blanding-visitor-center",
        "membership": "gold",
        "order": 13,
        "logo": "images/logos/visitors.png"
    },
    {
        "name": "Blanding City Wellness Center",
        "address": "1013 South 300 West Blanding Utah 84511",
        "phone": "(435) 678-3457",
        "website": "https://www.blanding-ut.gov/wellness-center",
        "membership": "silver",
        "order": 14,
        "logo": "images/logos/wellness.png"
    },
    {
        "name": "Homestead Steak House",
        "address": "121 E Center St Blanding UT 84511",
        "phone": "(435) 678-3456",
        "website": "https://www.homesteadsteakhouseut.com",
        "membership": "bronze",
        "order": 15,
        "logo": "images/logos/steak.png"
        },
        {
        "name": "Blue Mountain Artisans",
        "address": "215 E Center St Blanding UT 84511",
        "phone": "(435) 678-3456",
        "website": "https://www.facebook.com/Blue-Mountain-Artisans",
        "membership": "gold",
        "order": 16,
        "logo": "images/logos/art.png"
    }
 ]

 }
